mockaroo/__init__.py
mockaroo/__main__.py
mockaroo/cli.py
mockaroo/client.py
mockaroo/exceptions.py
mockaroo/layout.py
mockaroo_python-3.0.0.dist-info/LICENSE
mockaroo_python-3.0.0.dist-info/METADATA
mockaroo_python-3.0.0.dist-info/WHEEL
mockaroo_python-3.0.0.dist-info/entry_points.txt
mockaroo_python-3.0.0.dist-info/RECORD
